PyDSWS/__init__.py
PyDSWS/datastream.py
PyDSWS-tr/__init__.py
PyDSWS-tr/datastream.py
PyDSWS_tr-0.9.dist-info/METADATA
PyDSWS_tr-0.9.dist-info/RECORD
PyDSWS_tr-0.9.dist-info/WHEEL
PyDSWS_tr-0.9.dist-info/top_level.txt
